Metadata-Version: 2.1
Name: django-real-content
Version: 0.1.12
Summary: Template tags to quickly show real content instead of lorem ipsum.
Home-page: https://github.com/mislavcimpersak/django-real-content
Author: Mislav Cimperšak
Author-email: mislav.cimpersak@gmail.com
License: MIT
Download-URL: https://github.com/mislavcimpersak/django-real-content/tarball/0.1.12
Keywords: django real content lorem ipsum
Platform: UNKNOWN
Classifier: Development Status :: 4 - Beta
Classifier: Environment :: Web Environment
Classifier: Framework :: Django
Classifier: Framework :: Django :: 1.6
Classifier: Framework :: Django :: 1.7
Classifier: Framework :: Django :: 1.8
Classifier: Framework :: Django :: 1.9
Classifier: Framework :: Django :: 1.10
Classifier: Framework :: Django :: 1.11
Classifier: Framework :: Django :: 2.0
Classifier: Framework :: Django :: 2.1
Classifier: Intended Audience :: Developers
Classifier: License :: OSI Approved :: MIT License
Classifier: Operating System :: OS Independent
Classifier: Programming Language :: Python
Classifier: Programming Language :: Python :: 2.7
Classifier: Programming Language :: Python :: 3
Classifier: Programming Language :: Python :: 3.4
Classifier: Programming Language :: Python :: 3.5
Classifier: Programming Language :: Python :: 3.6
Classifier: Programming Language :: Python :: 3.7
Classifier: Framework :: Django
Classifier: Topic :: Internet :: WWW/HTTP
Classifier: Topic :: Software Development :: Libraries :: Python Modules
Requires-Dist: Django (>=1.6)
Requires-Dist: beautifulsoup4 (>=4.3)
